buildkite_sdk/__init__.py
buildkite_sdk/environment.py
buildkite_sdk/schema.py
buildkite_sdk/sdk.py
cnunciato_buildkite_sdk-0.0.51.dist-info/METADATA
cnunciato_buildkite_sdk-0.0.51.dist-info/WHEEL
cnunciato_buildkite_sdk-0.0.51.dist-info/RECORD
