Metadata-Version: 2.4
Name: cnunciato-buildkite-sdk
Version: 0.0.51
Summary: Automatically generated by Nx.
Requires-Python: <4,>=3.9
Requires-Dist: pyyaml
